{
 "slug": "post-222071651426",
 "title": "쯩으로 내 증명서를 한 번에!",
 "date": "2020.08.26",
 "sort": 1598429293999,
 "cat": "insight",
 "topics": [
  "broof",
  "did"
 ],
 "desc": "증명서에 대해 알아보아요 내 증명서를 한 번에! 이제 쯩으로 한 번에 관리하세요 필요할 때 찾기 어렵고 매번 새로 발급받아야 하는 증명서, 관리하기 너",
 "lead": "증명서에 대해 알아보아요",
 "hero_img": "assets/blog/post-222071651426/fig-1.png",
 "read_min": 1,
 "blocks": [
  {
   "t": "p",
   "html": "내 증명서를 한 번에!"
  },
  {
   "t": "img",
   "src": "assets/blog/post-222071651426/fig-1.png"
  },
  {
   "t": "list",
   "items": [
    "이제 쯩으로 한 번에 관리하세요",
    "필요할 때 찾기 어렵고 매번 새로 발급받아야 하는 증명서, 관리하기 너무 힘드셨죠?",
    "이제 사용은 간편하고 관리는 안전한 쯩으로 증명서를 관리해 보세요."
   ]
  },
  {
   "t": "p",
   "html": "내 증명서를 한 곳에"
  },
  {
   "t": "p",
   "html": "이곳저곳 흩어져 있는 증명서 이제 ‘쯩’에서 한 번에 관리하세요."
  },
  {
   "t": "img",
   "src": "assets/blog/post-222071651426/fig-2.png"
  },
  {
   "t": "p",
   "html": "버튼 하나로 끝나는 증명서 제출"
  },
  {
   "t": "p",
   "html": "더 이상 일일이 찾아다닐 필요 없이 ‘쯩’에서 증명서를 바로 제출하세요."
  },
  {
   "t": "img",
   "src": "assets/blog/post-222071651426/fig-3.png"
  },
  {
   "t": "list",
   "items": [
    "블록체인에 보관되는 내 증명서",
    "소중한 내 개인 정보, 걱정하지 마세요.",
    "해킹이 불가능한 블록체인으로 내 증명서 정보를 안전하게 보관합니다."
   ]
  },
  {
   "t": "img",
   "src": "assets/blog/post-222071651426/fig-4.png"
  },
  {
   "t": "list",
   "items": [
    "채용 시 필요한 증명서를 제출하는 서비스는 하반기에 추가될 예정입니다.",
    "현재는 broof 증명서 불러오기 기능만 가능합니다."
   ]
  },
  {
   "t": "img",
   "src": "assets/blog/post-222071651426/fig-5.png"
  }
 ]
}