{
 "slug": "post-222276328210",
 "title": "서울시, 블록체인 기반의 ‘비대면 자격검증‘을 '공공서비스 예약'에 적용",
 "date": "2021.03.15",
 "sort": 1615802018365,
 "cat": "insight",
 "topics": [
  "payments",
  "tech"
 ],
 "desc": "안녕하세요, 아이콘루프입니다. 오늘 15일, 서울시는 블록체인 기반의 ‘비대면 자격검증‘을 ‘서울시 공공서비스예약’ 홈페이지(https://yeyak.seoul.…",
 "lead": "안녕하세요, 아이콘루프입니다.",
 "hero_img": null,
 "read_min": 4,
 "blocks": [
  {
   "t": "p",
   "html": "오늘 15일, 서울시는 블록체인 기반의 ‘비대면 자격검증‘을 ‘서울시 공공서비스예약’ 홈페이지(https://yeyak.seoul.go.kr/web/main.do)에 적용한다고 밝혔습니다."
  },
  {
   "t": "p",
   "html": "아이콘루프에서 개발한 블록체인 코어 엔진 ‘루프체인‘이 적용된 서울시 블록체인 표준 플랫폼 기반의 ‘비대면 자격검증’을 통해, 홈페이지에서 본인인증만 하면 기존에 현장에서 제출해야 했던 총 9종의 증빙서류를 디지털로 제출할 수 있게 되며 블록체인을 통해 본인인증 및 전자서명이 이루어지기 때문에 위변조 방지 및 개인정보 보호도 강화됩니다."
  },
  {
   "t": "p",
   "html": "블록체인 기술이 일상에 하나씩 스며들며 우리가 살아가는 세상을 보다 편리하고 신뢰할 수 있도록 만들어가고 있습니다. 아이콘루프는 블록체인 기술을 통해 지속적으로 일상을 혁신해 나가도록 하겠습니다."
  },
  {
   "t": "p",
   "html": "감사합니다."
  },
  {
   "t": "p",
   "html": "Life Meets Blockchain"
  },
  {
   "t": "p",
   "html": "기사원문 (출처) : https://www.asiae.co.kr/article/2021031218371504949"
  },
  {
   "t": "p",
   "html": "서울시, 7000개 '공공서비스 예약' 전면 개편…비대면 요금감면"
  },
  {
   "t": "p",
   "html": "[아시아경제 임철영 기자] 서울시가 ‘공공서비스 예약’ 홈페이지와 예약 서비스를 전면 개편해 대폭 확대한다. 공공서비스 예약 홈페이지는 서울시와 산하기관, 25개 자치구에서 제공하는 공공서비스를 온라인으로 예약·결제하는 통합 플랫폼이다."
  },
  {
   "t": "p",
   "html": "15일 서울시에 따르면 카카오톡 인공지능 상담사 챗봇 ‘서울톡‘에 공공서비스 예약기능을 신설한다. 채팅창에 원하는 내용을 입력만 하면 서울시가 운영하는 체육시설부터 대관시설, 문화·교육 프로그램, 시립병원 진료까지 총 7000여개의 공공서비스를 예약할 수 있다."
  },
  {
   "t": "p",
   "html": "새로운 공공서비스 예약은 ▲카카오톡 챗봇 ‘서울톡’ 예약·상담 개시 ▲스마트폰 환경 최적화 홈페이지 개편 ▲블록체인 기반 이용료 감면대상 비대면 검증 도입 등을 골자로 한다."
  },
  {
   "t": "p",
   "html": "공공서비스예약 홈페이지 회원이 아니더라도 카카오톡만 있으면 누구나 공공서비스를 예약할 수 있도록 ‘서울톡’ 예약서비스를 신설했다. 국내 많은 스마트폰 사용자가 이용 중인 플랫폼인 만큼 공공서비스 예약절차가 대폭 간소화될 전망이다. 특히 챗봇 예약은 카카오톡에 가입된 휴대전화 번호로 본인확인을 하기 때문에 최초 1회 사용자 인증만 하면 이후부터는 추가 인증 없이 바로 예약이 가능하다."
  },
  {
   "t": "p",
   "html": "홈페이지도 스마트폰 예약 증가 추세를 반영해 스마트폰에 최적화된 환경으로 개편하고 로그인·결제 등 이용절차도 간소화한다. 위치기반 서비스, 관심정보 설정 같이 이용자 맞춤형 메뉴도 대폭 추가한다. 문자·영상으로 의사소통을 중계해주는 ‘손말이음센터’ 바로가기 등 고령자·장애인을 위한 의사소통 서비스도 새롭게 지원한다."
  },
  {
   "t": "p",
   "html": "블록체인 기술을 기반으로 한 ‘비대면 자격검증‘도 도입한다. 현재 기초생활수급자, 장애인, 국가유공자 등은 공공시설 이용시 요금감면 혜택을 받을 수 있는데 관련 증빙서류를 발급받아서 서비스 이용시 제출해야 하는 불편함이 있다."
  },
  {
   "t": "p",
   "html": "‘비대면 자격검증’은 공공시설 이용요금 감면대상자가 홈페이지 상에서 본인 인증을 하면 증빙서류 총 9종을 종이서류 대신 디지털로 제출할 수 있는 방식이다. 데이터 위변조가 원천 불가한 블록체인 기술로 본인인증과 전자서명이 이뤄지기 때문에 개인정보 보호도 강화된다."
  },
  {
   "t": "p",
   "html": "이원목 서울시 스마트도시정책관은 “현재 4차 산업혁명이라는 거대한 산업생태계 변화와 더불어 코로나19로 인한 시민일상의 변화를 마주하고 있다“며 “시민들이 서울시가 제공하는 다양한 시설과 교육·문화서비스를 스마트폰으로 편리하게 예약하고 이용할 수 있도록 최신 스마트기술을 적재적소에 적용해 서비스를 개선해 나가겠다. 이용가능한 시설과 문화콘텐츠도 지속적으로 확대하겠다“고 말했다."
  }
 ]
}